fastmcp_test/__init__.py
fastmcp_test-0.1.0.dist-info/METADATA
fastmcp_test-0.1.0.dist-info/WHEEL
fastmcp_test-0.1.0.dist-info/entry_points.txt
fastmcp_test-0.1.0.dist-info/RECORD
